LICENSE
syslog_ng_cfg_helper/__init__.py
syslog_ng_cfg_helper/build_db.py
syslog_ng_cfg_helper/console.py
syslog_ng_cfg_helper/driver_db/__init__.py
syslog_ng_cfg_helper/driver_db/block.py
syslog_ng_cfg_helper/driver_db/driver.py
syslog_ng_cfg_helper/driver_db/driver_db.py
syslog_ng_cfg_helper/driver_db/exceptions.py
syslog_ng_cfg_helper/driver_db/option.py
syslog_ng_cfg_helper/driver_db/utils.py
syslog_ng_cfg_helper/generate_diff.py
syslog_ng_cfg_helper/globals.py
syslog_ng_cfg_helper/module_loader/__init__.py
syslog_ng_cfg_helper/module_loader/load_modules.py
syslog_ng_cfg_helper/module_loader/parse_sentence.py
syslog_ng_cfg_helper/syslog-ng-cfg-helper.db
syslog_ng_cfg_helper-1.8.1.dist-info/LICENSE
syslog_ng_cfg_helper-1.8.1.dist-info/METADATA
syslog_ng_cfg_helper-1.8.1.dist-info/WHEEL
syslog_ng_cfg_helper-1.8.1.dist-info/entry_points.txt
syslog_ng_cfg_helper-1.8.1.dist-info/RECORD
