Metadata-Version: 2.1
Name: syslog-ng-cfg-helper
Version: 1.8.1
Summary: Configuration helper for syslog-ng.
Home-page: https://github.com/alltilla/syslog-ng-cfg-helper
License: GPL-3.0-only
Keywords: syslog-ng,configuration,cfg
Author: Attila Szakacs
Author-email: szakacs.attila96@gmail.com
Requires-Python: >=3.8,<4.0
Classifier: Environment :: Console
Classifier: License :: OSI Approved :: GNU General Public License v3 (GPLv3)
Classifier: Operating System :: OS Independent
Classifier: Programming Language :: Python :: 3
Classifier: Programming Language :: Python :: 3.8
Classifier: Programming Language :: Python :: 3.9
Classifier: Programming Language :: Python :: 3.10
Classifier: Programming Language :: Python :: 3.11
Classifier: Programming Language :: Python :: 3.12
Classifier: Topic :: System :: Networking
Classifier: Topic :: System :: Systems Administration
Requires-Dist: pyright (>=1.1.322,<2.0.0)
Project-URL: Repository, https://github.com/alltilla/syslog-ng-cfg-helper
